songpress/CompositePropertyPanel.pot
songpress/CompositePropertyPanel.py
songpress/DecoSlider.py
songpress/EditDistance.py
songpress/Editor.py
songpress/Enumerate.py
songpress/FontComboBox.py
songpress/FontFaceDialog.pot
songpress/FontFaceDialog.py
songpress/Globals.py
songpress/HTML.py
songpress/ListDialog.pot
songpress/ListDialog.py
songpress/MyDecoSlider.py
songpress/MyListDialog.py
songpress/MyNormalizeDialog.py
songpress/MyNotationDialog.py
songpress/MyPreferences.pot
songpress/MyPreferencesDialog.pot
songpress/MyPreferencesDialog.py
songpress/MyTransposeDialog.py
songpress/MyUpdateDialog.pot
songpress/MyUpdateDialog.py
songpress/MyUpdatePanel.py
songpress/NormalizeDialog.pot
songpress/NormalizeDialog.py
songpress/NotationDialog.pot
songpress/NotationDialog.py
songpress/Pref.py
songpress/PrefTest.py
songpress/Preferences.pot
songpress/Preferences.py
songpress/PreferencesDialog.pot
songpress/PreferencesDialog.py
songpress/PreviewCanvas.pot
songpress/PreviewCanvas.py
songpress/Renderer.py
songpress/SDIMainFrame.pot
songpress/SDIMainFrame.py
songpress/SimplePropertyPanel.pot
songpress/SongBoxes.py
songpress/SongDecorator.py
songpress/SongFormat.py
songpress/SongTokenizer.py
songpress/SongpressFrame.pot
songpress/SongpressFrame.py
songpress/Tokenizer.py
songpress/Transpose.pot
songpress/Transpose.py
songpress/TransposeDialog.pot
songpress/TransposeDialog.py
songpress/UpdateDialog.pot
songpress/UpdateDialog.py
songpress/UpdatePanel.pot
songpress/UpdatePanel.py
songpress/__init__.py
songpress/decorators/StandardVerseNumbers.py
songpress/decorators/__init__.py
songpress/dev_tool.py
songpress/errdlg.pot
songpress/errdlg.py
songpress/i18n.py
songpress/img/chord.png
songpress/img/chorus.png
songpress/img/copy.png
songpress/img/copyAsImage.png
songpress/img/copyAsImage2.png
songpress/img/cut.png
songpress/img/labelVerses.png
songpress/img/new.png
songpress/img/open.png
songpress/img/paste.png
songpress/img/pasteChords.png
songpress/img/redo.png
songpress/img/save.png
songpress-1.9.0.dist-info/METADATA
songpress-1.9.0.dist-info/WHEEL
songpress-1.9.0.dist-info/entry_points.txt
songpress-1.9.0.dist-info/RECORD
