Metadata-Version: 2.4
Name: songpress
Version: 1.9.0
Summary: Songpress is a free, easy to use song typeset program for Windows and Linux, that generates high-quality songbooks.
License: GNU GPL v2
Author: Luca Allulli
Author-email: luca@skeed.it
Requires-Python: >=3.9
Classifier: License :: Other/Proprietary License
Classifier: Programming Language :: Python :: 3
Classifier: Programming Language :: Python :: 3.9
Classifier: Programming Language :: Python :: 3.10
Classifier: Programming Language :: Python :: 3.11
Classifier: Programming Language :: Python :: 3.12
Classifier: Programming Language :: Python :: 3.13
Classifier: Programming Language :: Python :: 3.14
Requires-Dist: pyshortcuts (>=1.9.5,<2.0.0)
Requires-Dist: python-pptx (>=1.0.2,<2.0.0)
Requires-Dist: requests (>=2.32.4,<3.0.0)
Requires-Dist: wxPython (>=4.2.4,<5.0.0)
Project-URL: Homepage, https://www.skeed.it/songpress
Project-URL: Issues, https://github.com/lallulli/songpress/issues
Project-URL: Source, https://github.com/lallulli/songpress
